xladybug/__init__.py
xladybug/debugger.py
xladybug-0.1.1.dist-info/METADATA
xladybug-0.1.1.dist-info/WHEEL
xladybug-0.1.1.dist-info/top_level.txt
xladybug-0.1.1.dist-info/RECORD
